bugprove/__main__.py
bugprove/cli.py
bugprove/client.py
bugprove/internal/__init__.py
bugprove/internal/api/__init__.py
bugprove/internal/api/families_api.py
bugprove/internal/api/links_api.py
bugprove/internal/api/reports_api.py
bugprove/internal/api/scans_api.py
bugprove/internal/api/token_api.py
bugprove/internal/api/upload_api.py
bugprove/internal/api_client.py
bugprove/internal/api_response.py
bugprove/internal/configuration.py
bugprove/internal/exceptions.py
bugprove/internal/models/__init__.py
bugprove/internal/models/api_error_code.py
bugprove/internal/models/begin_indirect_upload_request.py
bugprove/internal/models/begin_indirect_upload_response.py
bugprove/internal/models/begin_multipart_indirect_upload_request.py
bugprove/internal/models/begin_multipart_indirect_upload_response.py
bugprove/internal/models/cancel_indirect_upload_request.py
bugprove/internal/models/component_category.py
bugprove/internal/models/continue_multipart_indirect_upload_request.py
bugprove/internal/models/continue_multipart_indirect_upload_response.py
bugprove/internal/models/create_link_request.py
bugprove/internal/models/create_link_response.py
bugprove/internal/models/cvss.py
bugprove/internal/models/cvss_vector.py
bugprove/internal/models/cvss_version.py
bugprove/internal/models/default_scan_configuration.py
bugprove/internal/models/download_response.py
bugprove/internal/models/error_response.py
bugprove/internal/models/family_response.py
bugprove/internal/models/family_type.py
bugprove/internal/models/finding_response.py
bugprove/internal/models/finding_state.py
bugprove/internal/models/finding_summary.py
bugprove/internal/models/finding_summary_finding_counts.py
bugprove/internal/models/finding_summary_unconfirmed_finding_counts.py
bugprove/internal/models/finding_type.py
bugprove/internal/models/known_vulnerability_filter.py
bugprove/internal/models/link_role.py
bugprove/internal/models/list_families_response.py
bugprove/internal/models/list_scans_response.py
bugprove-1.0.0.dist-info/LICENSE
bugprove-1.0.0.dist-info/METADATA
bugprove-1.0.0.dist-info/WHEEL
bugprove-1.0.0.dist-info/entry_points.txt
bugprove-1.0.0.dist-info/RECORD
