Metadata-Version: 2.1
Name: bugprove
Version: 1.0.0
Summary: CLI and client library for BugProve
Home-page: https://bugprove.com/
License: MIT
Author: BugProve, Inc.
Author-email: support@bugprove.com
Requires-Python: >=3.8,<3.13
Classifier: Environment :: Console
Classifier: License :: OSI Approved :: MIT License
Classifier: Operating System :: OS Independent
Classifier: Programming Language :: Python :: 3
Classifier: Programming Language :: Python :: 3.8
Classifier: Programming Language :: Python :: 3.9
Classifier: Programming Language :: Python :: 3.10
Classifier: Programming Language :: Python :: 3.11
Classifier: Programming Language :: Python :: 3.12
Classifier: Programming Language :: Python :: 3 :: Only
Classifier: Topic :: Security
Requires-Dist: aenum (>=3.1.15,<4.0.0)
Requires-Dist: aiohttp (>=3.10.5,<4.0.0)
Requires-Dist: aiohttp-retry (>=2.8.3,<3.0.0)
Requires-Dist: click (>=8.1.7,<9.0.0)
Requires-Dist: pydantic (>=2.8.2,<3.0.0)
Requires-Dist: pyjwt (>=2.9.0,<3.0.0)
Requires-Dist: python-dateutil (>=2.9.0.post0,<3.0.0)
Requires-Dist: tqdm (>=4.66.5,<5.0.0)
Requires-Dist: typing-extensions (>=4.12.2,<5.0.0)
Requires-Dist: urllib3 (>=1.25.3,<2.1.0)
